{
  "name": "adapt-contrib-narrative",
  "version": "6.5.4",
  "framework": ">=5.17.2",
  "homepage": "https://github.com/adaptlearning/adapt-contrib-narrative",
  "bugs": "https://github.com/adaptlearning/adapt-contrib-narrative/issues",
  "component": "narrative",
  "targetAttribute": "_narrative",
  "displayName": "Narrative",
  "description": "A component that displays an image gallery with accompanying text",
  "main": "/js/adapt-contrib-narrative.js",
  "keywords": [
    "adapt-plugin",
    "adapt-component"
  ],
  "license": "GPL-3.0",
  "_release": "6.5.4",
  "_resolution": {
    "type": "version",
    "tag": "v6.5.4",
    "commit": "450efc9fcc75a8b9995d5cb0d9050a1d72862199"
  },
  "_source": "https://github.com/adaptlearning/adapt-contrib-narrative.git",
  "_target": "6.5.4",
  "_originalSource": "adapt-contrib-narrative"
}